AUTHORS
MANIFEST.in
README.rst
UNLICENSE
setup.py
yatiblog/__init__.py
yatiblog/main.py
yatiblog/rst.py
yatiblog.egg-info/PKG-INFO
yatiblog.egg-info/SOURCES.txt
yatiblog.egg-info/dependency_links.txt
yatiblog.egg-info/entry_points.txt
yatiblog.egg-info/requires.txt
yatiblog.egg-info/top_level.txt
yatiblog.egg-info/zip-safe