Metadata-Version: 1.0
Name: yatiblog
Version: 1.0.1
Summary: Static site generator for blogs and source code documentation
Home-page: https://github.com/tav/yatiblog
Author: tav
Author-email: tav@espians.com
License: Public Domain
Keywords: blog,documentation
Platform: UNKNOWN
Classifier: Development Status :: 5 - Production/Stable
Classifier: Environment :: Web Environment
Classifier: Intended Audience :: Developers
Classifier: License :: Public Domain
Classifier: Operating System :: OS Independent
Classifier: Programming Language :: Python
Classifier: Topic :: Documentation
Classifier: Topic :: Text Processing
Classifier: Topic :: Utilities
